google_documents/__init__.py
google_documents/settings.py
google_documents/entities/__init__.py
google_documents/entities/api_service_mixin.py
google_documents/entities/file.py
google_documents/entities/from_itemable.py
google_documents/entities/manager.py
google_documents/utils/__init__.py
google_documents/utils/pandas.py
google_documents-0.0.3.dist-info/METADATA
google_documents-0.0.3.dist-info/RECORD
google_documents-0.0.3.dist-info/WHEEL
google_documents-0.0.3.dist-info/top_level.txt
