Metadata-Version: 2.1
Name: google-documents
Version: 0.0.3
Summary: Python package to work with Google Documents
Home-page: http://github.com/chimplie/google-documents
Author: Vitalii Pavliuk
Author-email: pavliuk96@gmail.com
License: MIT
Platform: UNKNOWN
Requires-Dist: google-api-python-client (==1.6.6)
Requires-Dist: pandas (==0.23.4)
